config_loader.py
main.py
mcp_server.py
ssh_manager.py
ssh_agent_mcp-0.3.1.dist-info/METADATA
ssh_agent_mcp-0.3.1.dist-info/WHEEL
ssh_agent_mcp-0.3.1.dist-info/entry_points.txt
ssh_agent_mcp-0.3.1.dist-info/top_level.txt
ssh_agent_mcp-0.3.1.dist-info/RECORD
