Metadata-Version: 2.4
Name: ssh_agent_mcp
Version: 0.3.1
Summary: SSH Agent MCP服务 - 支持SSH连接管理、命令执行和SFTP文件传输的完整MCP服务器
Home-page: https://github.com/yourusername/sshagent
Author: Your Name
Author-email: Your Name <your.email@example.com>
License: MIT
Project-URL: Homepage, https://github.com/yourusername/sshagent
Project-URL: Repository, https://github.com/yourusername/sshagent
Project-URL: Documentation, https://github.com/yourusername/sshagent#readme
Project-URL: Bug Tracker, https://github.com/yourusername/sshagent/issues
Keywords: mcp,ssh,remote,automation,claude,sftp,file-transfer
Classifier: Development Status :: 4 - Beta
Classifier: Intended Audience :: Developers
Classifier: License :: OSI Approved :: MIT License
Classifier: Programming Language :: Python :: 3
Classifier: Programming Language :: Python :: 3.12
Classifier: Topic :: System :: Networking
Classifier: Topic :: Software Development :: Libraries :: Python Modules
Requires-Python: >=3.12
Requires-Dist: mcp>=1.0.0
Requires-Dist: paramiko>=3.0.0
Requires-Dist: pydantic>=2.0.0
Provides-Extra: dev
Requires-Dist: pytest>=7.0.0; extra == "dev"
Requires-Dist: pytest-asyncio>=0.21.0; extra == "dev"
Requires-Dist: black>=23.0.0; extra == "dev"
Requires-Dist: ruff>=0.1.0; extra == "dev"
Requires-Dist: build>=0.10.0; extra == "dev"
Dynamic: author
Dynamic: home-page
Dynamic: requires-python
